vid2seq/__init__.py
vid2seq-0.0.1.dev0.dist-info/METADATA
vid2seq-0.0.1.dev0.dist-info/WHEEL
vid2seq-0.0.1.dev0.dist-info/top_level.txt
vid2seq-0.0.1.dev0.dist-info/RECORD
